scripts/__init__.py
scripts/check_dataset_integrity.py
scripts/collect_demonstration.py
scripts/config_copy.py
scripts/convert_data_to_lerobot_openpi.py
scripts/convert_data_to_lerobot_smolvla.py
scripts/create_dataset.py
scripts/create_task_example.py
scripts/create_template.py
scripts/download_tasks.py
scripts/evaluate_policy.py
scripts/get_dataset_info.py
scripts/group_create_dataset.py
scripts/init_file_create.py
scripts/init_path.py
scripts/inspect_hdf5.py
scripts/manage_assets.py
scripts/map_tasks.py
scripts/package_all_suites.py
scripts/random_sample_hdf5.py
scripts/regenerate_dataset.py
scripts/replace_prismatic_imports.py
scripts/visualize_bddl.py
vla_arena/__init__.py
vla_arena/cli/__init__.py
vla_arena/cli/eval.py
vla_arena/cli/main.py
vla_arena/cli/train.py
vla_arena/configs/evaluation/openpi.yaml
vla_arena/configs/evaluation/openvla.yaml
vla_arena/configs/evaluation/openvla_oft.yaml
vla_arena/configs/evaluation/random.yaml
vla_arena/configs/evaluation/smolvla.yaml
vla_arena/configs/evaluation/univla.yaml
vla_arena/configs/train/openpi.yaml
vla_arena/configs/train/openvla.yaml
vla_arena/configs/train/openvla_oft.yaml
vla_arena/configs/train/smolvla.yaml
vla_arena/configs/train/univla.yaml
vla_arena/models/openpi/evaluator.py
vla_arena/models/openpi/trainer.py
vla_arena/models/openpi/examples/convert_jax_model_to_pytorch.py
vla_arena/models/openpi/examples/simple_client/main.py
vla_arena/models/openpi/examples/vla_arena/eval_vla_arena.py
vla_arena/models/openpi/packages/openpi-client/src/openpi_client/__init__.py
vla_arena/models/openpi/packages/openpi-client/src/openpi_client/action_chunk_broker.py
vla_arena/models/openpi/packages/openpi-client/src/openpi_client/base_policy.py
vla_arena/models/openpi/packages/openpi-client/src/openpi_client/image_tools.py
vla_arena/models/openpi/packages/openpi-client/src/openpi_client/image_tools_test.py
vla_arena/models/openpi/packages/openpi-client/src/openpi_client/msgpack_numpy.py
vla_arena-1.0.0.dist-info/licenses/LICENSE
vla_arena-1.0.0.dist-info/METADATA
vla_arena-1.0.0.dist-info/WHEEL
vla_arena-1.0.0.dist-info/eager_resources.txt
vla_arena-1.0.0.dist-info/entry_points.txt
vla_arena-1.0.0.dist-info/top_level.txt
vla_arena-1.0.0.dist-info/RECORD
