Metadata-Version: 2.4
Name: vla-arena
Version: 1.0.0
Summary: VLA-Arena: An Open-Source Framework for Benchmarking Vision-Language-Action Models
Author: Borong Zhang, Jiachen Shen
Author-email: Jiahao Li <jiahaoli2077@gmail.com>
License: Apache-2.0
Project-URL: Homepage, https://vla-arena.github.io
Project-URL: Repository, https://github.com/PKU-Alignment/VLA-Arena
Project-URL: Documentation, https://github.com/PKU-Alignment/VLA-Arena/docs
Project-URL: Bug Report, https://github.com/PKU-Alignment/VLA-Arena/issues
Keywords: Vision-Language-Action,VLA Models,Robotic Manipulation,Benchmark
Classifier: Programming Language :: Python :: 3.11
Classifier: Intended Audience :: Science/Research
Classifier: Topic :: Scientific/Engineering :: Artificial Intelligence
Classifier: Topic :: Software Development :: Libraries :: Python Modules
Requires-Python: >=3
License-File: LICENSE
Requires-Dist: imageio[ffmpeg]
Requires-Dist: robosuite==1.5.1
Requires-Dist: bddl
Requires-Dist: easydict
Requires-Dist: cloudpickle
Requires-Dist: gym
Requires-Dist: numpy==1.26.4
Requires-Dist: pytest>=7.0.0
Requires-Dist: pytest-cov>=4.0.0
Requires-Dist: pytest-mock>=3.10.0
Requires-Dist: torch
Requires-Dist: h5py
Requires-Dist: matplotlib
Requires-Dist: tensorflow
Provides-Extra: openvla
Requires-Dist: accelerate>=0.25.0; extra == "openvla"
Requires-Dist: draccus==0.8.0; extra == "openvla"
Requires-Dist: einops; extra == "openvla"
Requires-Dist: huggingface_hub; extra == "openvla"
Requires-Dist: json-numpy; extra == "openvla"
Requires-Dist: jsonlines; extra == "openvla"
Requires-Dist: matplotlib; extra == "openvla"
Requires-Dist: peft==0.11.1; extra == "openvla"
Requires-Dist: protobuf; extra == "openvla"
Requires-Dist: rich; extra == "openvla"
Requires-Dist: sentencepiece==0.1.99; extra == "openvla"
Requires-Dist: timm==0.9.10; extra == "openvla"
Requires-Dist: tokenizers==0.19.1; extra == "openvla"
Requires-Dist: torch==2.2.0; extra == "openvla"
Requires-Dist: torchvision==0.17.0; extra == "openvla"
Requires-Dist: torchaudio==2.2.0; extra == "openvla"
Requires-Dist: transformers==4.40.1; extra == "openvla"
Requires-Dist: wandb; extra == "openvla"
Requires-Dist: tensorflow==2.15.0; extra == "openvla"
Requires-Dist: tensorflow_datasets==4.9.3; extra == "openvla"
Requires-Dist: tensorflow_graphics==2021.12.3; extra == "openvla"
Provides-Extra: openvla-oft
Requires-Dist: accelerate>=0.25.0; extra == "openvla-oft"
Requires-Dist: draccus==0.8.0; extra == "openvla-oft"
Requires-Dist: einops; extra == "openvla-oft"
Requires-Dist: huggingface_hub; extra == "openvla-oft"
Requires-Dist: json-numpy; extra == "openvla-oft"
Requires-Dist: jsonlines; extra == "openvla-oft"
Requires-Dist: matplotlib; extra == "openvla-oft"
Requires-Dist: peft==0.11.1; extra == "openvla-oft"
Requires-Dist: protobuf; extra == "openvla-oft"
Requires-Dist: rich; extra == "openvla-oft"
Requires-Dist: sentencepiece==0.1.99; extra == "openvla-oft"
Requires-Dist: timm==0.9.10; extra == "openvla-oft"
Requires-Dist: tokenizers==0.19.1; extra == "openvla-oft"
Requires-Dist: torch==2.2.0; extra == "openvla-oft"
Requires-Dist: torchvision==0.17.0; extra == "openvla-oft"
Requires-Dist: torchaudio==2.2.0; extra == "openvla-oft"
Requires-Dist: transformers==4.40.1; extra == "openvla-oft"
Requires-Dist: wandb; extra == "openvla-oft"
Requires-Dist: tensorflow==2.15.0; extra == "openvla-oft"
Requires-Dist: tensorflow_datasets==4.9.3; extra == "openvla-oft"
Requires-Dist: tensorflow_graphics==2021.12.3; extra == "openvla-oft"
Requires-Dist: diffusers==0.30.3; extra == "openvla-oft"
Requires-Dist: imageio; extra == "openvla-oft"
Requires-Dist: uvicorn; extra == "openvla-oft"
Requires-Dist: fastapi; extra == "openvla-oft"
Requires-Dist: json-numpy; extra == "openvla-oft"
Provides-Extra: univla
Requires-Dist: absl-py==2.1.0; extra == "univla"
Requires-Dist: accelerate==0.32.1; extra == "univla"
Requires-Dist: braceexpand==0.1.7; extra == "univla"
Requires-Dist: draccus==0.8.0; extra == "univla"
Requires-Dist: einops==0.8.1; extra == "univla"
Requires-Dist: ema-pytorch==0.5.1; extra == "univla"
Requires-Dist: gym==0.26.2; extra == "univla"
Requires-Dist: h5py==3.11.0; extra == "univla"
Requires-Dist: huggingface-hub==0.26.1; extra == "univla"
Requires-Dist: hydra-core==1.3.2; extra == "univla"
Requires-Dist: imageio==2.34.2; extra == "univla"
Requires-Dist: jsonlines==4.0.0; extra == "univla"
Requires-Dist: lightning==2.4.0; extra == "univla"
Requires-Dist: matplotlib==3.10.1; extra == "univla"
Requires-Dist: moviepy==1.0.3; extra == "univla"
Requires-Dist: numpy==1.26.4; extra == "univla"
Requires-Dist: omegaconf==2.3.0; extra == "univla"
Requires-Dist: opencv-python==4.10.0.84; extra == "univla"
Requires-Dist: packaging==24.1; extra == "univla"
Requires-Dist: peft==0.11.1; extra == "univla"
Requires-Dist: Pillow==11.2.1; extra == "univla"
Requires-Dist: piq==0.8.0; extra == "univla"
Requires-Dist: pyquaternion==0.9.9; extra == "univla"
Requires-Dist: pytorch-lightning==1.8.6; extra == "univla"
Requires-Dist: PyYAML==6.0.1; extra == "univla"
Requires-Dist: Requests==2.32.3; extra == "univla"
Requires-Dist: rich==14.0.0; extra == "univla"
Requires-Dist: robosuite==1.5.1; extra == "univla"
Requires-Dist: rotary-embedding-torch==0.8.4; extra == "univla"
Requires-Dist: setuptools==57.5.0; extra == "univla"
Requires-Dist: tensorflow==2.15.0; extra == "univla"
Requires-Dist: tensorflow-datasets==4.9.3; extra == "univla"
Requires-Dist: tensorflow-graphics==2021.12.3; extra == "univla"
Requires-Dist: termcolor==3.0.1; extra == "univla"
Requires-Dist: timm==0.9.10; extra == "univla"
Requires-Dist: tokenizers==0.19.1; extra == "univla"
Requires-Dist: torch==2.2.0; extra == "univla"
Requires-Dist: torchvision==0.17.0; extra == "univla"
Requires-Dist: tqdm==4.66.4; extra == "univla"
Requires-Dist: transformers==4.40.1; extra == "univla"
Requires-Dist: webdataset==0.2.111; extra == "univla"
Requires-Dist: wandb; extra == "univla"
Provides-Extra: smolvla
Requires-Dist: datasets<=3.6.0,>=2.19.0; extra == "smolvla"
Requires-Dist: diffusers>=0.27.2; extra == "smolvla"
Requires-Dist: huggingface-hub[cli,hf-transfer]==0.34.2; extra == "smolvla"
Requires-Dist: cmake>=3.29.0.1; extra == "smolvla"
Requires-Dist: einops>=0.8.0; extra == "smolvla"
Requires-Dist: opencv-python-headless>=4.9.0; extra == "smolvla"
Requires-Dist: av>=14.2.0; extra == "smolvla"
Requires-Dist: jsonlines>=4.0.0; extra == "smolvla"
Requires-Dist: packaging>=24.2; extra == "smolvla"
Requires-Dist: pynput>=1.7.7; extra == "smolvla"
Requires-Dist: pyserial>=3.5; extra == "smolvla"
Requires-Dist: wandb==0.20.0; extra == "smolvla"
Requires-Dist: torch==2.7.1; extra == "smolvla"
Requires-Dist: torchcodec<0.6.0,>=0.2.1; (sys_platform != "win32" and (sys_platform != "linux" or (platform_machine != "aarch64" and platform_machine != "arm64" and platform_machine != "armv7l")) and (sys_platform != "darwin" or platform_machine != "x86_64")) and extra == "smolvla"
Requires-Dist: torchvision==0.22.1; extra == "smolvla"
Requires-Dist: draccus==0.10.0; extra == "smolvla"
Requires-Dist: gymnasium==0.29.1; extra == "smolvla"
Requires-Dist: rerun-sdk==0.22.1; extra == "smolvla"
Requires-Dist: deepdiff<9.0.0,>=7.0.1; extra == "smolvla"
Requires-Dist: flask<4.0.0,>=3.0.3; extra == "smolvla"
Requires-Dist: imageio[ffmpeg]==2.37.0; extra == "smolvla"
Requires-Dist: termcolor==3.1.0; extra == "smolvla"
Requires-Dist: transformers==4.51.3; extra == "smolvla"
Requires-Dist: num2words==0.5.14; extra == "smolvla"
Requires-Dist: accelerate==1.7.0; extra == "smolvla"
Requires-Dist: safetensors==0.4.3; extra == "smolvla"
Requires-Dist: lerobot>=2.0.0; extra == "smolvla"
Requires-Dist: draccus; extra == "smolvla"
Provides-Extra: openpi
Requires-Dist: augmax>=0.3.4; extra == "openpi"
Requires-Dist: dm-tree>=0.1.8; extra == "openpi"
Requires-Dist: einops>=0.8.0; extra == "openpi"
Requires-Dist: equinox>=0.11.8; extra == "openpi"
Requires-Dist: flatbuffers>=24.3.25; extra == "openpi"
Requires-Dist: flax==0.10.2; extra == "openpi"
Requires-Dist: fsspec[gcs]>=2024.6.0; extra == "openpi"
Requires-Dist: gym-aloha>=0.1.1; extra == "openpi"
Requires-Dist: imageio>=2.36.1; extra == "openpi"
Requires-Dist: jax[cuda12]==0.5.3; extra == "openpi"
Requires-Dist: jaxtyping==0.2.36; extra == "openpi"
Requires-Dist: lerobot; extra == "openpi"
Requires-Dist: ml_collections==1.0.0; extra == "openpi"
Requires-Dist: numpy<2.0.0,>=1.22.4; extra == "openpi"
Requires-Dist: numpydantic>=1.6.6; extra == "openpi"
Requires-Dist: opencv-python>=4.10.0.84; extra == "openpi"
Requires-Dist: openpi-client; extra == "openpi"
Requires-Dist: orbax-checkpoint==0.11.13; extra == "openpi"
Requires-Dist: pillow>=11.0.0; extra == "openpi"
Requires-Dist: sentencepiece>=0.2.0; extra == "openpi"
Requires-Dist: torch==2.7.1; extra == "openpi"
Requires-Dist: tqdm-loggable>=0.2; extra == "openpi"
Requires-Dist: typing-extensions>=4.12.2; extra == "openpi"
Requires-Dist: tyro>=0.9.5; extra == "openpi"
Requires-Dist: wandb>=0.19.1; extra == "openpi"
Requires-Dist: filelock>=3.16.1; extra == "openpi"
Requires-Dist: beartype==0.19.0; extra == "openpi"
Requires-Dist: treescope>=0.1.7; extra == "openpi"
Requires-Dist: transformers==4.53.2; extra == "openpi"
Requires-Dist: rich>=14.0.0; extra == "openpi"
Requires-Dist: polars>=1.30.0; extra == "openpi"
Provides-Extra: lint
Requires-Dist: isort>=5.11.0; extra == "lint"
Requires-Dist: black>=23.1.0; extra == "lint"
Requires-Dist: pylint[spelling]>=2.15.0; extra == "lint"
Requires-Dist: mypy>=0.990; extra == "lint"
Requires-Dist: flake8; extra == "lint"
Requires-Dist: flake8-bugbear; extra == "lint"
Requires-Dist: flake8-comprehensions; extra == "lint"
Requires-Dist: flake8-docstrings; extra == "lint"
Requires-Dist: flake8-pyi; extra == "lint"
Requires-Dist: flake8-simplify; extra == "lint"
Requires-Dist: ruff>=0.4.0; extra == "lint"
Requires-Dist: doc8; extra == "lint"
Requires-Dist: pydocstyle; extra == "lint"
Requires-Dist: pyenchant; extra == "lint"
Requires-Dist: pre-commit; extra == "lint"
Provides-Extra: test
Requires-Dist: pytest>=7.0.0; extra == "test"
Requires-Dist: pytest-cov>=3.0.0; extra == "test"
Requires-Dist: pytest-xdist>=2.5.0; extra == "test"
Provides-Extra: docs
Requires-Dist: sphinx>=5.0.0; extra == "docs"
Requires-Dist: sphinx-autoapi; extra == "docs"
Requires-Dist: sphinx-autobuild; extra == "docs"
Requires-Dist: sphinx-copybutton; extra == "docs"
Requires-Dist: sphinx-autodoc-typehints; extra == "docs"
Requires-Dist: myst-parser; extra == "docs"
Dynamic: license-file
Dynamic: requires-python
